{"01": {"added": ["4646456.ee", "4fund.ee", "6245.ee", "699.ee", "adis.ee", "ag86.ee", "airportstay.ee", "alcornlabs.ee", "alicorn.ee", "alicornlabs.ee", "asennus.ee", "balticstorageplatform.ee", "baufix.ee", "bayliner.ee", "brimeri.ee", "casta.ee", "deegy.ee", "delo.ee", "devdrive.ee", "e-delica.ee", "ecomove.ee", "elers.ee", "elumeri.ee", "em-art.ee", "eptl.ee", "erika6.ee", "erikakodud.ee", "essential.ee", "exenum.ee", "firmakuller.ee", "fitprana.ee", "froconpro.ee", "fruitiki.ee", "hallimae.ee", "hoiansind.ee", "homegarden.ee", "hppuidukoda.ee", "inhome.ee", "j-net.ee", "jjy.ee", "jss.ee", "kieselstein.ee", "kiilirahvakool.ee", "kingiidee24.ee", "koolimeedia.ee", "kultuuripartnerlus.ee", "kummituba.ee", "lembituhotel.ee", "listudio.ee", "mutin.ee", "narvasalsa.ee", "nommetennis.ee", "oseyo.ee", "paardujs.ee", "paunkulapuhkemaja.ee", "peoplaan.ee", "perfectbags.ee", "pg33.ee", "pikadpatsid.ee", "ralliauto.ee", "ralliautod.ee", "ralliexport.ee", "rallyexport.ee", "rehvi24.ee", "rendisaun.ee", "renditooline.ee", "residences.ee", "scaftech.ee", "sjy.ee", "solarum.ee", "species.ee", "stuudiocirrus.ee", "svkviimistlus.ee", "taskukalli.ee", "thugg.ee", "today.ee", "torukratt.ee", "tudengile.ee", "valgusolendid.ee", "vebelo.ee", "venakor.ee", "victoria-tech.ee", "vpwood.ee", "wonge.ee", "xn--vidusidud-q7ae.ee", "xn--vidusit-10ae.ee", "yayaki.ee", "ye9.ee"], "deleted": ["adapterm.ee", "arab.ee", "arop.ee", "automobus.ee", "avenu.ee", "bbird.ee", "behome.ee", "brewmix.ee", "caravanrent24.ee", "carhub.ee", "conciergeforyou.ee", "cymuraisec.ee", "eestitekstiil.ee", "epoekeskus.ee", "feelzsolutions.ee", "gridelin2.ee", "hobusalutalu.ee", "iran.ee", "itellusfood.ee", "katijamatiraamat.ee", "klaosekummut.ee", "kvarkagency.ee", "ky5568.ee", "lahutusavaldus.ee", "nobedik.ee", "ork.ee", "ravintola.ee", "renuva.ee", "retromuuseum.ee", "superbody.ee", "teadmistetugi.ee", "timberhaus.ee", "usdc.ee", "vnp.ee", "xn--tarktnn-r2a.ee", "yhendus.ee"], "timestamp": 1722477072.3259048}, "02": {"added": ["18w.ee", "2022.ee", "2ww.ee", "3destate.ee", "6mm.ee", "6nn.ee", "6ww.ee", "88n.ee", "88x.ee", "8xx.ee", "8zz.ee", "99n.ee", "9nn.ee", "9zz.ee", "apple.com.ee", "astekonehitus.ee", "asx.ee", "axvar.ee", "b2bmarketing.ee", "balticdataanalytics.ee", "balticweld.ee", "beautyspot.ee", "biochar.ee", "bso.ee", "clickable.ee", "discikool.ee", "dongfeng.ee", "dongfengbox.ee", "dongfengmotors.ee", "download.ee", "ds8.ee", "eatrading.ee", "eco-fuel.ee", "ehitusasu.ee", "esgkeskkond.ee", "ewanala.ee", "forthing.ee", "gerdarentel.ee", "graciasport.ee", "hansa24.ee", "hentula.ee", "homacares.ee", "intiim.ee", "italicus.ee", "k52.ee", "k53.ee", "k54.ee", "kkkk.ee", "koertehoid.ee", "kwonestonia.ee", "lumiz.ee", "maketistuudio.ee", "mangula.ee", "meediataju.ee", "mini-caravan.ee", "minikaravan.ee", "mkaksviis.ee", "mroremont.ee", "nai.ee", "nzz.ee", "paemurru.ee", "paulhunter.ee", "poseidon-detailing.ee", "promptr.ee", "rimaehitus.ee", "rohenool.ee", "roosipuu.ee", "ropkaliiv.ee", "sce.ee", "sudamesonumid.ee", "sushipro.ee", "systemone.ee", "toetankultuuri.ee", "travelest.ee", "tuurmann.ee", "ukrainakeskus.ee", "vaan.ee", "ventspets.ee", "vosajapuu.ee", "vvvv.ee", "xn--jgar-0qa.ee", "xn--lkpildur-n4aa.ee", "xn--logistikapev-pcb.ee", "xn--mngula-bua.ee", "yourspecialstyle.ee"], "deleted": ["123merele.ee", "786.ee", "a48.ee", "a555.ee", "a88.ee", "a888.ee", "a99.ee", "a999.ee", "aeroauto.ee", "amg24.ee", "ant-company.ee", "arsvask.ee", "ayx20.ee", "baarbaltijaamas.ee", "bikes24.ee", "carfest.ee", "carhunter.ee", "emtk.ee", "estonia2025.ee", "estonians2025.ee", "evosad.ee", "expo2025.ee", "freeze.ee", "garage55.ee", "greenbox.ee", "huudskoor.ee", "joli.ee", "kurla.ee", "laminat.ee", "legarage.ee", "lellekas.ee", "lkp.ee", "marmary.ee", "metaboxsolutions.ee", "mg24.ee", "mikklemberg.ee", "misjoniseiklus.ee", "muslik.ee", "p96.ee", "polyvalent.ee", "premiumride.ee", "ralliruum.ee", "rebelant.ee", "roxtone.ee", "rprent.ee", "salus-smarthome.ee", "stepupsolutions.ee", "tallinn2025.ee", "teslaparts.ee", "toidupisik.ee", "tokyo2025expo.ee", "triaad.ee", "viljandimois.ee", "viru-autospa.ee", "warmtech.ee", "xn--viljandimis-nfb.ee", "xn--vrvikuningas-gcb.ee"], "timestamp": 1722563214.4065084}}