{"01": {"added": ["2628.ee", "317.ee", "5116.ee", "5558.ee", "582.ee", "598.ee", "659.ee", "692.ee", "723.ee", "7o.ee", "abtehno.ee", "agal.ee", "aidevelopment.ee", "asgardsolution.ee", "driven.ee", "easyco.ee", "eesla.ee", "elektriautoabi.ee", "elektriautoabi24.ee", "elektriautohooldus.ee", "elektriautoremont.ee", "fitnesschallenge.ee", "freshvibe.ee", "genialistid.ee", "goby.ee", "grillandmore.ee", "itsaboy.ee", "jankofalt.ee", "jq88.ee", "jq99.ee", "kotlander.ee", "leiaabi.ee", "lifeful.ee", "lifery.ee", "minumaa.ee", "ns1.template.ee", "ns2.template.ee", "ouse.ee", "plakat.ee", "puiduoutlet.ee", "rudiment.ee", "soleronenergy.ee", "superstudy.ee", "tempel.ee", "toidupakid.ee", "tselovek.ee", "webassistent.ee", "woodslab.ee", "xiaoc.ee", "xn--ruge-0qa.ee", "xn--viispevakohvik-9hb.ee", "zq88.ee"], "deleted": ["368.ee", "5566.ee", "7755.ee", "8866.ee", "academie.ee", "aivoputinlits.ee", "artmed.ee", "balticvitamins.ee", "bcacham.ee", "chrc.ee", "cleveronmobility.ee", "dubs.ee", "eetris.ee", "estonianfanarmy.ee", "eurorasolutions.ee", "framour.ee", "freyanna.ee", "frigotaimed.ee", "glassmet.ee", "gloriamarts.ee", "grillvoileib.ee", "haldja.ee", "hallkardinal.ee", "hoidja.ee", "homoprimussapiens.ee", "immi.ee", "inksveeb.ee", "internationalquality.ee", "internationaltv.ee", "jaluta.ee", "jeslin.ee", "jnice.ee", "kr-rehvid.ee", "kuuki.ee", "latuk.ee", "lavida.ee", "liugvarav.ee", "makeuplbl.ee", "matex.ee", "metrup.ee", "mgistore.ee", "newhuo.ee", "ofrelo.ee", "opetajaoninimene.ee", "ostaeestikunsti.ee", "pauerprim.ee", "pawleashclub.ee", "peipsigrupp.ee", "personaprimusgata.ee", "priimuladisain.ee", "puhkuselaen.ee", "puuvilla24.ee", "raamatutakso.ee", "ramen.ee", "reeststart.ee", "roger-gallet.ee", "saunatreila.ee", "scanhk.ee", "sharpstone.ee", "sinuvari.ee", "sinuvarjus.ee", "sleepin.ee", "soulfood.ee", "sovelu.ee", "teemekorda.ee", "terveeluteejuht.ee", "ticketworld.ee", "toitumisnoustaja.ee", "tuhkatriinuteenused.ee", "ulc.ee", "vahvadasjad.ee", "varjus.ee", "vineeriturg.ee", "xn--e-zgac.ee", "xn--thik-0ra.ee"], "timestamp": 1696124635.9355857}, "02": {"added": ["9993.ee", "9996.ee", "absurdik.ee", "akgym.ee", "arheoloogideliit.ee", "ceer.ee", "child-city.ee", "dataduo.ee", "ehitusload.ee", "esmaabistaja.ee", "everol.ee", "fp2.ee", "freshjuiceblender.ee", "galerii1826.ee", "hakailustuudio.ee", "hiiulada.ee", "hiiuretro.ee", "insidetech.ee", "justnii.ee", "katariinamartens.ee", "khdisain.ee", "magicblend.ee", "markepol.ee", "miamor.ee", "mindnurture.ee", "minukliinik.ee", "mlkpuhastus.ee", "molevad.ee", "muudatusprojekt.ee", "omsystems.ee", "oskan-aidata.ee", "rahuhouses.ee", "redhand.ee", "rezerv.ee", "septikum.ee", "stratup.ee", "tailormade.ee", "tekstiilipuhatus.ee", "vellexdigital.ee", "winbig.ee"], "deleted": ["2022.ee", "293.ee", "admelius.ee", "aice.ee", "altme.ee", "amarane.ee", "autobuksiir.ee", "baaricatering.ee", "balttimber.ee", "bhpex.ee", "bigthr.ee", "bingold.ee", "bluepartner.ee", "brighterfuture.ee", "buksiir.ee", "careers.ee", "coachingekspert.ee", "crafideo.ee", "credeo.ee", "degoogle.ee", "detailers.ee", "digikond.ee", "dynamicbridge.ee", "ewa.ee", "finemang.ee", "firmast.ee", "fisun.ee", "fourguys.ee", "hingetuba.ee", "igrushka.ee", "ikv.ee", "juhtivcoaching.ee", "kaleander.ee", "kava1.ee", "kingfa.ee", "kodoform.ee", "kohvi1.ee", "krdesigned.ee", "lastmile.ee", "lauracircling.ee", "ledipood.ee", "lineanatura.ee", "lionstone.ee", "lisainiki.ee", "looduslik.ee", "mairi.ee", "midsona.ee", "minudomeen200.ee", "muruladu.ee", "nelliscakeart.ee", "ns.inlink.ee", "ns1.clothesforyou.ee", "ns2.clothesforyou.ee", "papillonkids.ee", "pg6.ee", "pilgupuudja.ee", "punapargi.ee", "retruck.ee", "shail.ee", "simrace.ee", "simraceestonia.ee", "smartme.ee", "tty.ee", "vabadusetee.ee", "vgautokool.ee", "wagner.ee", "worldgift.ee"], "timestamp": 1696210739.8993323}, "03": {"added": ["3dmandala.ee", "417.ee", "823.ee", "acee.ee", "ainsaar.ee", "air2life.ee", "air2live.ee", "aln.ee", "arde.ee", "axax.ee", "beautyforyou.ee", "classemini.ee", "detailers.ee", "e-medical.ee", "ecl.ee", "eestit.ee", "elleste.ee", "et.ee", "exitravel.ee", "experium.ee", "firmaraamat.ee", "hufi.ee", "inrisky.ee", "internships.ee", "jnr.ee", "kayakshop.ee", "konseptum.ee", "kotlin.ee", "laascloud.ee", "laheperevilla.ee", "livida.ee", "luxa.ee", "maarvan.ee", "mankius.ee", "menetluskonverents.ee", "mindfully.ee", "mooble.ee", "pakendilahendused.ee", "pasternak.ee", "pepetr.ee", "praktikakeskus.ee", "premico.ee", "psolution.ee", "puhastusteekond.ee", "pussycats.ee", "rahaguru.ee", "rehekuun.ee", "rppluss.ee", "rtmedia.ee", "saltlake.ee", "selectcreate.ee", "shrub.ee", "swedtrac.ee", "tooleidja.ee", "viivika.ee", "viivikavahi.ee", "webcontext.ee", "winter24.ee", "xn--hupallid-d4a.ee", "xn--kotermo-80a.ee", "xn--pikesepargihooldus-ltb.ee", "xn--raanda-9ta.ee", "xn--tleidja-90aa.ee", "zparki.ee"], "deleted": ["a33.ee", "arion.ee", "atea-mobil.ee", "atea-mobile.ee", "ateamobil.ee", "ateamobile.ee", "benestruct.ee", "cocktailservice.ee", "coctails.ee", "coregrow.ee", "cybersages.ee", "dear.ee", "ecuadoroy.ee", "ehh.ee", "elustiilimentor.ee", "esimenemalevkond.ee", "esproventus.ee", "form.ee", "hostb.ee", "hrm.ee", "imilab.ee", "italwax.ee", "kippis.ee", "kivikatused.ee", "kombogrupp.ee", "kunstiteraapiatuba.ee", "led-service.ee", "madenotinchina.ee", "melania.ee", "merekaardid.ee", "ningbo.ee", "nordcargobridge.ee", "poliitika.ee", "scripta.ee", "siinonhea.ee", "sinariehitus.ee", "targaltaustraaliasse.ee", "toreon.ee", "turvateenused.ee", "veovan.ee", "vorkpall.ee", "waalex.ee", "winerz.ee", "xn--nnefoorum-p7a.ee", "xn--vrkpall-10a.ee", "yessolutions.ee"], "timestamp": 1696297123.9496357}, "04": {"added": ["11media.ee", "6kla.ee", "8000.ee", "a.ee", "aitutor.ee", "ankhict.ee", "artin.ee", "artius.ee", "artiuscentre.ee", "artiuskeskus.ee", "atvpood.ee", "autohindaja.ee", "ballers.ee", "bbq-koolitus.ee", "bbqkool.ee", "bbqkoolitus.ee", "birico.ee", "brandboostco.ee", "burgerwrap.ee", "cr3at1ve.ee", "crossfitviljandi.ee", "cryberit.ee", "cryptoprofit.ee", "doner.ee", "dora.ee", "dovgil.ee", "droonikoolitused.ee", "dutchjobs.ee", "fiks.ee", "form.ee", "freedesign.ee", "fucknordpool.ee", "glassmet.ee", "haljastusfirma.ee", "hariduskoolitus.ee", "harjuara.ee", "healthcare.ee", "healthtech.ee", "heloskin.ee", "hiiukiviaed.ee", "hrm.ee", "ilapothecary.ee", "innasidoruk.ee", "iridium.ee", "kaskema.ee", "kiili-majad.ee", "kiiltoshop.ee", "kilgirantso.ee", "kodo.ee", "koolivaheaeg.ee", "koristusteenustartus.ee", "krfventure.ee", "kusmurahaon.ee", "kvaliteedikeskus.ee", "leecougan.ee", "liivatera.ee", "lostnfound.ee", "medcenter.ee", "medstaff.ee", "menrex.ee", "metsakorraldajad.ee", "mhuvikool.ee", "misasja.ee", "modulhus.ee", "myhealth.ee", "myinvests.ee", "myny.ee", "myoviv.ee", "niger.ee", "nutivere.ee", "oog.ee", "palgimees.ee", "pallistpallita.ee", "payticket.ee", "podcastistuudio.ee", "prestigemotors.ee", "puhastuskeemia.ee", "pusled.ee", "puslepood.ee", "qhealth.ee", "r63.ee", "rentplus.ee", "rentpluss.ee", "rosewise.ee", "sarp.ee", "scripta.ee", "seitsesammu.ee", "siitsinna.ee", "sinuosteopaat.ee", "soorleiton.ee", "speedfit.ee", "spm.ee", "steelike.ee", "studyhelp.ee", "tmmrou.ee", "toppak.ee", "torkpaber.ee", "vanaparnu.ee", "viimsi-majad.ee", "vorupesumaja.ee", "www.hingeharmoonia.ee", "xn--srp-qla.ee", "xn--tuletkketd-6bbqa.ee", "xn--veskimemuusikatalu-qtb.ee", "zhukov.ee"], "deleted": ["adminiac.ee", "airol.ee", "ajavarjud.ee", "ampatery.ee", "astrapharm.ee", "auto24finants.ee", "auto24liising.ee", "b52.ee", "bailsman.ee", "bauprof.ee", "eekualkrosmann.ee", "eflora.ee", "ehituslaen.ee", "ep00d.ee", "fideelia.ee", "franzmuller.ee", "gaijin.ee", "hhcshop.ee", "hingeelamused.ee", "hive.ee", "inhousepay.ee", "itrepo.ee", "jaanusroos.ee", "kadririnaldo.ee", "karlrattus.ee", "konspekt.ee", "kristiinatohv.ee", "laksuamet.ee", "majesi.ee", "meelik.ee", "meiega.ee", "meridetox.ee", "mesilake.ee", "mestorosta.ee", "michelada.ee", "minukodukas.ee", "mooddisain.ee", "mtecmoobel.ee", "muhumesilane.ee", "navatristan.ee", "ohutu.ee", "ohver.ee", "oskus.ee", "paksuamet.ee", "paperart.ee", "partnerthrowdown.ee", "pesahooldus.ee", "pillejaerkipulm.ee", "praam.ee", "radiovolna.ee", "salumesi.ee", "serveripark.ee", "serveriruum.ee", "skyweld.ee", "teekondarendajaks.ee", "toetameid.ee", "tulekulla.ee", "valgekriit.ee", "vcl.ee", "vladilena.com.ee", "wiruswim.ee", "xn--histuraamat-shb.ee", "xn--hmafm-gra.ee", "xn--laenmaksehirega-9kb.ee", "xn--rohepre-e1aa.ee", "xwds.ee"], "timestamp": 1696383593.0333397}}